{
  "cutoffs": [
{
      "cutoff": 10,
      "color": [
        0.2123,
        0.1,
        0.14563
      ]
},
{
      "cutoff": 20,
      "color": [
        0.1464,
        0.06323452,
        0.4565
      ]
},
    {
      "cutoff": 30,
      "color": [
        0.363,
        0.241,
        0.14356
      ]
    },
   {
      "cutoff": 50,
      "color": [
        0.6045,
        0.567,
        0.74532
      ]
   },
   {
      "cutoff": 75,
      "color": [
        0.4534,
        0.753,
        0.84534
      ]
   },
{
      "cutoff": 100,
      "color": [
        1.0,
        1.0,
        1.0
      ]
    }
  ],
  "width": 2000,
  "samples": 1000000000,
  "norm_cutoff": 2.0,
  "output_path": "Spike.png",
  "less_than": true
}
